mpsapi/__init__.py
mpsapi/logging_config.py
mpsapi/oz/__init__.py
mpsapi/oz/oz_client.py
mpsapi/wb/__init__.py
mpsapi/wb/wb_client.py
mpsapi/ym/__init__.py
mpsapi/ym/ym_client.py
mpsapi-0.0.9.dist-info/METADATA
mpsapi-0.0.9.dist-info/WHEEL
mpsapi-0.0.9.dist-info/entry_points.txt
mpsapi-0.0.9.dist-info/RECORD
