Metadata-Version: 2.4
Name: mpsapi
Version: 0.0.9
Summary: Асинхронные клиенты для маркетплейсов
Author-email: Dmitry Drozdov <ds.drozdov@gmail.com>
Requires-Python: >=3.13
Requires-Dist: aiohttp>=3.12.13
